dsphere/Datasphere.py
dsphere/__init__.py
dsphere/connectors.py
dsphere/defaults.py
dsphere/dfuncs.py
dsphere/ffuncs.py
dsphere/DataStream/__init__.py
dsphere/DataStream/archive.py
dsphere/DataStream/executors.py
dsphere/DataStream/file.py
dsphere/DataStream/load.py
dsphere/DataStream/macros.py
dsphere/DataStream/modelers.py
dsphere/DataStream/prefect.py
dsphere/DataStream/save.py
dsphere/DataStream/syncs.py
dsphere/FeatureSpace/__init__.py
dsphere/FeatureSpace/access.py
dsphere/FeatureSpace/add.py
dsphere/FeatureSpace/eval.py
dsphere/FeatureSpace/load.py
dsphere/FeatureSpace/metadata.py
dsphere/FeatureSpace/model.py
dsphere/FeatureSpace/transform.py
dsphere/FeatureSpace/view.py
dsphere/FeatureSpace/feature_structures/feature_chart.py
dsphere/FeatureSpace/feature_structures/feature_data.py
dsphere/FeatureSpace/feature_structures/feature_matrix.py
dsphere/FeatureSpace/feature_structures/feature_model.py
dsphere/FeatureSpace/feature_structures/feature_set.py
dsphere/FeatureSpace/feature_structures/feature_view.py
dsphere/properties/functions.py
dsphere/properties/plots.py
dsphere-0.0.7.dist-info/LICENSE
dsphere-0.0.7.dist-info/METADATA
dsphere-0.0.7.dist-info/WHEEL
dsphere-0.0.7.dist-info/top_level.txt
dsphere-0.0.7.dist-info/RECORD
