Metadata-Version: 2.1
Name: dsphere
Version: 0.0.7
Summary: An example package
Author-email: Example Author <author@example.com>
License: Copyright (c) 2019 Waterway Data LLC        
Classifier: Programming Language :: Python :: 3
Classifier: License :: OSI Approved :: MIT License
Classifier: Operating System :: OS Independent
Requires-Python: >=3.7
License-File: LICENSE
Requires-Dist: pandas
Requires-Dist: numpy
Requires-Dist: matplotlib
Requires-Dist: dask
Requires-Dist: pyarrow
Requires-Dist: scipy (<1.9.0,>=1.4.0)
Requires-Dist: scikit-learn (==1.0.0)
